Components/__init__.py
Components/data_ingestion.py
Components/data_transformation.py
Components/model_evalution.py
Components/model_trainer.py
database_automation/__init__.py
database_automation/mongo_crud.py
utils/__init__.py
utils/utils.py
MongoDbConnect_v1.0.0-0.0.4.dist-info/METADATA
MongoDbConnect_v1.0.0-0.0.4.dist-info/WHEEL
MongoDbConnect_v1.0.0-0.0.4.dist-info/top_level.txt
MongoDbConnect_v1.0.0-0.0.4.dist-info/RECORD
